ontology2transmart/__init__.py
ontology2transmart/__version__.py
ontology2transmart/dsv_reader.py
ontology2transmart/ontology2transmart.py
ontology2transmart/ontology_mapper.py
ontology2transmart/ontology_writer.py
ontology2transmart-0.1.2.dist-info/LICENSE
ontology2transmart-0.1.2.dist-info/METADATA
ontology2transmart-0.1.2.dist-info/WHEEL
ontology2transmart-0.1.2.dist-info/entry_points.txt
ontology2transmart-0.1.2.dist-info/top_level.txt
ontology2transmart-0.1.2.dist-info/RECORD
