Metadata-Version: 2.1
Name: ontology2transmart
Version: 0.1.2
Summary: Example ontology to TranSMART loader
Home-page: https://github.com/thehyve/python_ontology2transmart
Author: Gijs Kant
Author-email: gijs@thehyve.nl
License: GNU General Public License v3 or later
Keywords: ontology2transmart
Platform: UNKNOWN
Classifier: Development Status :: 2 - Pre-Alpha
Classifier: Intended Audience :: Developers
Classifier: Topic :: Scientific/Engineering :: Bio-Informatics
Classifier: License :: OSI Approved :: MIT License
Classifier: Natural Language :: English
Classifier: Programming Language :: Python :: 3
Classifier: Programming Language :: Python :: 3.6
Requires-Python: >=3.6.0
Requires-Dist: click (<8.0,>=7.0)
Requires-Dist: transmart-loader (<1.4.0,>=1.3.5)
Provides-Extra: dev
Requires-Dist: prospector[with_pyroma] ; extra == 'dev'
Requires-Dist: yapf ; extra == 'dev'
Requires-Dist: isort ; extra == 'dev'
